mcp_overkiz/__init__.py
mcp_overkiz/server.py
mseep_mcp_overkiz-0.1.3.dist-info/METADATA
mseep_mcp_overkiz-0.1.3.dist-info/WHEEL
mseep_mcp_overkiz-0.1.3.dist-info/entry_points.txt
mseep_mcp_overkiz-0.1.3.dist-info/top_level.txt
mseep_mcp_overkiz-0.1.3.dist-info/RECORD
