Metadata-Version: 2.4
Name: mseep-mcp-overkiz
Version: 0.1.3
Summary: MCP server for controlling lights using overkiz
Author-email: mseep <support@skydeck.ai>
Requires-Python: >=3.13.3
Requires-Dist: mcp>=1.7.1
Requires-Dist: pyoverkiz>=1.1.0
